mortal_func/__init__.py
mortal_func/func_main.cpython-311-x86_64-linux-gnu.so
mortal_func/function/__init__.py
mortal_func/function/dict_func.cpython-311-x86_64-linux-gnu.so
mortal_func/function/list_func.cpython-311-x86_64-linux-gnu.so
mortal_func/function/number_func.cpython-311-x86_64-linux-gnu.so
mortal_func/function/str_func.cpython-311-x86_64-linux-gnu.so
mortal_func-4.2.0.dist-info/METADATA
mortal_func-4.2.0.dist-info/WHEEL
mortal_func-4.2.0.dist-info/top_level.txt
mortal_func-4.2.0.dist-info/RECORD
